moodswing/__init__.py
moodswing/_version.py
moodswing/spacy_support.py
moodswing/cli/__init__.py
moodswing/cli/sample_plots.py
moodswing/data/__init__.py
moodswing/data/lexicons/afinn.pkl
moodswing/data/lexicons/bing.pkl
moodswing/data/lexicons/nrc.pkl
moodswing/data/lexicons/syuzhet_dict.pkl
moodswing/data/text/sample_novels.pkl
moodswing/lexicons/__init__.py
moodswing/lexicons/loader.py
moodswing/lexicons/types.py
moodswing/sentiment/__init__.py
moodswing/sentiment/dictionary.py
moodswing/sentiment/spacy_sentiment.py
moodswing/text/__init__.py
moodswing/text/sentences.py
moodswing/text/spacy_sentences.py
moodswing/text/tokens.py
moodswing/transforms/__init__.py
moodswing/transforms/core.py
moodswing/viz/__init__.py
moodswing/viz/trajectory.py
moodswing-0.1.0.dist-info/licenses/LICENSE
moodswing-0.1.0.dist-info/METADATA
moodswing-0.1.0.dist-info/WHEEL
moodswing-0.1.0.dist-info/entry_points.txt
moodswing-0.1.0.dist-info/top_level.txt
moodswing-0.1.0.dist-info/RECORD
