Metadata-Version: 2.4
Name: moodswing
Version: 0.1.0
Summary: Track changes in sentiment over narrative time.
Author-email: David Brown <dwb2@andrew.cmu.edu>
Maintainer-email: David Brown <dwb2@andrew.cmu.edu>
License-Expression: MIT
Project-URL: Documentation, https://browndw.github.io/moodswing
Project-URL: Homepage, https://github.com/browndw/moodswing
Keywords: nlp,language
Classifier: Programming Language :: Python :: 3 :: Only
Classifier: Programming Language :: Python :: 3.10
Classifier: Programming Language :: Python :: 3.11
Classifier: Programming Language :: Python :: 3.12
Classifier: Intended Audience :: Science/Research
Classifier: Topic :: Text Processing :: Linguistic
Classifier: Operating System :: OS Independent
Requires-Python: >=3.10
License-File: LICENSE
Requires-Dist: numpy>=1.22
Requires-Dist: matplotlib>=3.5
Requires-Dist: pandas>=1.5
Requires-Dist: pytest>=7.0
Requires-Dist: nltk>=3.9
Requires-Dist: spacy>=3.7
Requires-Dist: spacytextblob>=5.0
Provides-Extra: test
Requires-Dist: pytest>=7.0; extra == "test"
Requires-Dist: pytest-cov>=4.0; extra == "test"
Provides-Extra: dev
Requires-Dist: pytest>=7.0; extra == "dev"
Requires-Dist: pytest-cov>=4.0; extra == "dev"
Requires-Dist: build>=1.0.0; extra == "dev"
Requires-Dist: twine>=5.0.0; extra == "dev"
Dynamic: license-file
